pioupiou/__init__.py
pioupiou/avatar_generator.py
pioupiou/chooser.py
pioupiou/exceptions.py
pioupiou/utils.py
pioupiou-0.8.1.dist-info/LICENSE
pioupiou-0.8.1.dist-info/METADATA
pioupiou-0.8.1.dist-info/WHEEL
pioupiou-0.8.1.dist-info/top_level.txt
pioupiou-0.8.1.dist-info/RECORD
