Metadata-Version: 2.1
Name: pioupiou
Version: 0.8.1
Summary: A generator of avatar optimised to generate or random avatars based on multiple image layers
Home-page: https://framagit.org/inkhey/pioupiou
Author: Guénaël Muller
Author-email: inkey@inkey-art.net
License: UNKNOWN
Keywords: avatar
Platform: UNKNOWN
Classifier: Development Status :: 3 - Alpha
Classifier: Programming Language :: Python :: 3.6
Classifier: Programming Language :: Python :: 3.7
Classifier: Programming Language :: Python :: 3.8
Classifier: License :: OSI Approved :: MIT License
Requires-Python: >= 3.5
Requires-Dist: Pillow
Requires-Dist: name-me
Requires-Dist: dataclasses
Provides-Extra: dev
Requires-Dist: pytest ; extra == 'dev'
Requires-Dist: flake8 ; extra == 'dev'
Requires-Dist: isort ; extra == 'dev'
Requires-Dist: mypy ; extra == 'dev'
Requires-Dist: pre-commit ; extra == 'dev'
Requires-Dist: commitizen ; extra == 'dev'
Requires-Dist: black ; extra == 'dev'
Provides-Extra: testing
Requires-Dist: pytest ; extra == 'testing'
